{
  "_meta": {
    "io.modelcontextprotocol.registry/official": {
      "isLatest": true,
      "status": "active",
      "updatedAt": "2026-06-16T00:00:00Z"
    }
  },
  "server": {
    "$schema": "https://static.modelcontextprotocol.io/schemas/2025-12-11/server.schema.json",
    "name": "mcp/azure-devops",
    "title": "Azure DevOps",
    "description": "MCP server for interacting with Azure DevOps",
    "version": "2.7.0",
    "packages": [
      {
        "registryType": "npm",
        "registryBaseUrl": "https://registry.npmjs.org",
        "runtimeHint": "npx",
        "identifier": "@azure-devops/mcp",
        "transport": {
          "type": "stdio"
        }
      }
    ]
  }
}